pydex/__about__.py
pydex/__init__.py
pydex/containers.py
pydex/exc.py
pydex/util.py
pydex/dalvik/__init__.py
pydex/dalvik/constants.py
pydex/dalvik/executable.py
pydex/dalvik/models/__init__.py
pydex/dalvik/models/dalvik.py
pydex0-1.7.0.dist-info/METADATA
pydex0-1.7.0.dist-info/WHEEL
pydex0-1.7.0.dist-info/licenses/LICENSE
pydex0-1.7.0.dist-info/RECORD
