Metadata-Version: 2.3
Name: pydex0
Version: 1.7.0
Summary: Powerful, yet easy to use, python library for loading(and eventually writing) dex files.
Project-URL: Documentation, https://pydex.readthedocs.io/en/latest/
Project-URL: Issues, https://github.com/yntha/pydex0/issues
Project-URL: Source, https://github.com/yntha/pydex0
Author-email: yntha <126660548+yntha@users.noreply.github.com>
License-File: LICENSE
Classifier: Development Status :: 4 - Beta
Classifier: Programming Language :: Python
Classifier: Programming Language :: Python :: 3.11
Classifier: Programming Language :: Python :: 3.12
Classifier: Programming Language :: Python :: Implementation :: CPython
Classifier: Programming Language :: Python :: Implementation :: PyPy
Requires-Python: >=3.11
Requires-Dist: pydatastreams
Provides-Extra: docs
Requires-Dist: myst-parser; extra == 'docs'
Requires-Dist: shibuya; extra == 'docs'
Requires-Dist: sphinx; extra == 'docs'
Requires-Dist: sphinx-new-tab-link; extra == 'docs'
